[
    {
        "title": "Editorial Board",
        "url": "https://www.sciencedirect.com/science/article/pii/S2210650221001280"
    },
    {
        "title": "Utilizing dependence among variables in evolutionary algorithms for mixed-integer programming: A case study on multi-objective constrained portfolio optimization",
        "url": "https://www.sciencedirect.com/science/article/pii/S2210650221000894"
    },
    {
        "title": "Hyper-Heuristics to customise metaheuristics for continuous optimisation",
        "url": "https://www.sciencedirect.com/science/article/pii/S2210650221000961"
    },
    {
        "title": "Memetic search for vehicle routing with simultaneous pickup-delivery and time windows",
        "url": "https://www.sciencedirect.com/science/article/pii/S2210650221000882"
    },
    {
        "title": "Performance analysis of dynamic optimization algorithms using relative error distance",
        "url": "https://www.sciencedirect.com/science/article/pii/S2210650221000912"
    },
    {
        "title": "ME-MEOA/D",
        "url": "https://www.sciencedirect.com/science/article/pii/S2210650221001000"
    },
    {
        "title": "C",
        "url": "https://www.sciencedirect.com/science/article/pii/S2210650221001012"
    },
    {
        "title": "C",
        "url": "https://www.sciencedirect.com/science/article/pii/S2210650221000985"
    },
    {
        "title": ": Multiobjective constrained clustering through decomposition-based memetic elitism",
        "url": "https://www.sciencedirect.com/science/article/pii/S2210650221001061"
    },
    {
        "title": "A partition-based constrained multi-objective evolutionary algorithm",
        "url": "https://www.sciencedirect.com/science/article/pii/S221065022100105X"
    },
    {
        "title": "Optimization techniques and applications in fog computing: An exhaustive survey",
        "url": "https://www.sciencedirect.com/science/article/pii/S2210650221001188"
    }
]