[
  {
    "title": "Editorial",
    "url": "https://link.springer.com/article/10.1023/A:1019107117335"
  },
  {
    "title": "Experience with adaptive mobile applications in Odyssey",
    "url": "https://link.springer.com/article/10.1023/A:1019159101405"
  },
  {
    "title": "WaveVideo – An integrated approach to adaptive wireless video",
    "url": "https://link.springer.com/article/10.1023/A:1019111218243"
  },
  {
    "title": "A trace-based evaluation of adaptive error correction for a wireless local area network",
    "url": "https://link.springer.com/article/10.1023/A:1019163202314"
  },
  {
    "title": "An evaluation of quality of service characteristics of PACS packet channel",
    "url": "https://link.springer.com/article/10.1023/A:1019115319152"
  },
  {
    "title": "Handover management in Low Earth Orbit (LEO) satellite networks",
    "url": "https://link.springer.com/article/10.1023/A:1019167303222"
  }
]