[
    {
        "title": "Inside Front Cover - Editorial Board Page/Cover image legend if applicable",
        "url": "https://www.sciencedirect.com/science/article/pii/S1383762117304174"
    },
    {
        "title": "InSTechAH: Cost-effectively autoscaling smart computing hadoop cluster in private cloud",
        "url": "https://www.sciencedirect.com/science/article/pii/S1383762117302035"
    },
    {
        "title": "Multi-policy-aware MapReduce resource allocation and scheduling for smart computing cluster",
        "url": "https://www.sciencedirect.com/science/article/pii/S138376211730259X"
    },
    {
        "title": "SVM-based real-time hyperspectral image classifier on a manycore architecture",
        "url": "https://www.sciencedirect.com/science/article/pii/S1383762116302910"
    },
    {
        "title": "Towards decentralized system-level security for MPSoC-based embedded applications",
        "url": "https://www.sciencedirect.com/science/article/pii/S1383762117300322"
    },
    {
        "title": "Smart search space reduction for approximate computing: A low energy HEVC encoder case study",
        "url": "https://www.sciencedirect.com/science/article/pii/S1383762117300371"
    },
    {
        "title": "An automatized method to parameterize embedded stereo matching algorithms",
        "url": "https://www.sciencedirect.com/science/article/pii/S1383762117300383"
    },
    {
        "title": "Feedback for increased robustness of forwarding graphs in the cloud",
        "url": "https://www.sciencedirect.com/science/article/pii/S138376211730070X"
    },
    {
        "title": "FLOPSYNC-QACS: Quantization-aware clock synchronization for wireless sensor networks",
        "url": "https://www.sciencedirect.com/science/article/pii/S1383762117300620"
    },
    {
        "title": "End-to-end timing analysis of cause-effect chains in automotive embedded systems",
        "url": "https://www.sciencedirect.com/science/article/pii/S1383762117300681"
    },
    {
        "title": "Using data visualization technique to detect sensitive information re-identification problem of real open dataset",
        "url": "https://www.sciencedirect.com/science/article/pii/S1383762117301145"
    }
]